odoo/addons/stock_picking_volume/README.rst
odoo/addons/stock_picking_volume/__init__.py
odoo/addons/stock_picking_volume/__manifest__.py
odoo/addons/stock_picking_volume/hooks.py
odoo/addons/stock_picking_volume/i18n/it.po
odoo/addons/stock_picking_volume/i18n/stock_picking_volume.pot
odoo/addons/stock_picking_volume/models/__init__.py
odoo/addons/stock_picking_volume/models/product_product.py
odoo/addons/stock_picking_volume/models/stock_move.py
odoo/addons/stock_picking_volume/models/stock_picking.py
odoo/addons/stock_picking_volume/readme/CONTRIBUTORS.md
odoo/addons/stock_picking_volume/readme/CREDITS.md
odoo/addons/stock_picking_volume/readme/DESCRIPTION.md
odoo/addons/stock_picking_volume/readme/USAGE.md
odoo/addons/stock_picking_volume/static/description/icon.png
odoo/addons/stock_picking_volume/static/description/index.html
odoo/addons/stock_picking_volume/tests/__init__.py
odoo/addons/stock_picking_volume/tests/test_stock_picking_volume.py
odoo/addons/stock_picking_volume/views/stock_move.xml
odoo/addons/stock_picking_volume/views/stock_picking.xml
odoo_addon_stock_picking_volume-18.0.1.0.0.7.dist-info/METADATA
odoo_addon_stock_picking_volume-18.0.1.0.0.7.dist-info/WHEEL
odoo_addon_stock_picking_volume-18.0.1.0.0.7.dist-info/top_level.txt
odoo_addon_stock_picking_volume-18.0.1.0.0.7.dist-info/RECORD
