Metadata-Version: 2.1
Name: odoo-addon-stock_picking_volume
Version: 18.0.1.0.0.7
Requires-Python: >=3.10
Requires-Dist: odoo-addon-product_dimension==18.0.*
Requires-Dist: odoo==18.0.*
Summary: Compute volume information on stock moves and pickings
Home-page: https://github.com/OCA/stock-logistics-warehouse
License: AGPL-3
Author: ACSONE SA/NV,Odoo Community Association (OCA)
Author-email: support@odoo-community.org
Classifier: Programming Language :: Python
Classifier: Framework :: Odoo
Classifier: Framework :: Odoo :: 18.0
Classifier: License :: OSI Approved :: GNU Affero General Public License v3
Classifier: Development Status :: 4 - Beta
